odoo/addons/company_dependent_attribute/README.rst
odoo/addons/company_dependent_attribute/__init__.py
odoo/addons/company_dependent_attribute/__manifest__.py
odoo/addons/company_dependent_attribute/i18n/company_dependent_attribute.pot
odoo/addons/company_dependent_attribute/i18n/es.po
odoo/addons/company_dependent_attribute/i18n/zh_CN.po
odoo/addons/company_dependent_attribute/models/__init__.py
odoo/addons/company_dependent_attribute/models/field.py
odoo/addons/company_dependent_attribute/readme/CONTRIBUTORS.rst
odoo/addons/company_dependent_attribute/readme/DESCRIPTION.rst
odoo/addons/company_dependent_attribute/static/description/icon.png
odoo/addons/company_dependent_attribute/static/description/index.html
odoo/addons/company_dependent_attribute/static/description/screen1.png
odoo/addons/company_dependent_attribute/views/field_view.xml
odoo13_addon_company_dependent_attribute-13.0.1.0.1.dev8.dist-info/METADATA
odoo13_addon_company_dependent_attribute-13.0.1.0.1.dev8.dist-info/WHEEL
odoo13_addon_company_dependent_attribute-13.0.1.0.1.dev8.dist-info/top_level.txt
odoo13_addon_company_dependent_attribute-13.0.1.0.1.dev8.dist-info/RECORD
